mcp_filesystem/__init__.py
mcp_filesystem/__main__.py
mcp_filesystem/advanced.py
mcp_filesystem/grep.py
mcp_filesystem/operations.py
mcp_filesystem/security.py
mcp_filesystem/server.py
mseep_mcp_filesystem-0.2.4.dist-info/METADATA
mseep_mcp_filesystem-0.2.4.dist-info/WHEEL
mseep_mcp_filesystem-0.2.4.dist-info/entry_points.txt
mseep_mcp_filesystem-0.2.4.dist-info/licenses/LICENSE
mseep_mcp_filesystem-0.2.4.dist-info/RECORD
