Metadata-Version: 2.4
Name: mseep-mcp-filesystem
Version: 0.2.4
Summary: MCP server for filesystem search and manipulation with granular search, content search and file edits
Author-email: mseep <support@skydeck.ai>
License: MIT
License-File: LICENSE
Keywords: ai,claude,fastmcp,filesystem,mcp
Classifier: License :: OSI Approved :: MIT License
Classifier: Operating System :: OS Independent
Classifier: Programming Language :: Python :: 3
Classifier: Programming Language :: Python :: 3.10
Classifier: Programming Language :: Python :: 3.11
Classifier: Programming Language :: Python :: 3.12
Classifier: Topic :: System :: Filesystems
Classifier: Topic :: Text Processing :: Filters
Classifier: Topic :: Utilities
Requires-Python: >=3.10
Requires-Dist: fastmcp>=0.4.0
Requires-Dist: typer>=0.9.0
Requires-Dist: typing-extensions>=4.6.0
Provides-Extra: dev
Requires-Dist: mypy>=1.9.0; extra == 'dev'
Requires-Dist: pre-commit>=3.6.0; extra == 'dev'
Requires-Dist: pytest-asyncio>=0.23.0; extra == 'dev'
Requires-Dist: pytest-cov>=5.0.0; extra == 'dev'
Requires-Dist: pytest>=8.1.1; extra == 'dev'
Requires-Dist: ruff>=0.3.0; extra == 'dev'
Requires-Dist: tomli-w>=1.0.0; extra == 'dev'
Requires-Dist: tomli>=2.0.1; extra == 'dev'
